PyWavTool/PyWavTool.py
PyWavTool/__init__.py
PyWavTool/dat.py
PyWavTool/length_string.py
PyWavTool/whd.py
PyWavTool-0.0.1.dist-info/LICENSE
PyWavTool-0.0.1.dist-info/METADATA
PyWavTool-0.0.1.dist-info/WHEEL
PyWavTool-0.0.1.dist-info/top_level.txt
PyWavTool-0.0.1.dist-info/RECORD
