Metadata-Version: 2.1
Name: PyWavTool
Version: 0.0.1
Summary: UTAU's wavtool emulater
Home-page: https://github.com/delta-kimigatame/PyWavTool
Author: delta_kimigatame
Author-email: sankaku.kuro@gmail.com
License: UNKNOWN
Project-URL: Bug Tracker, https://github.com/delta-kimigatame/PyWavTool/issues
Platform: UNKNOWN
Classifier: Programming Language :: Python :: 3
Classifier: License :: OSI Approved :: MIT License
Classifier: Operating System :: OS Independent
Requires-Python: >=3.7
License-File: LICENSE
Requires-Dist: numpy
